color_fprint/__init__.py
color_fprint-1.0.0.dist-info/METADATA
color_fprint-1.0.0.dist-info/WHEEL
color_fprint-1.0.0.dist-info/top_level.txt
color_fprint-1.0.0.dist-info/RECORD
