Metadata-Version: 2.4
Name: color_fprint
Version: 1.0.0
Summary: Impresión de texto coloreado y variables en consola
Author-email: Juan Manuel <juanmadiaz108@gmail.com>
License: MIT
Requires-Python: >=3.7
